{
  "obsidian-pandoc:pandoc-export-pdf": [
    {
      "modifiers": [
        "Mod",
        "Shift"
      ],
      "key": "P"
    }
  ],
  "app:go-back": [
    {
      "modifiers": [
        "Alt"
      ],
      "key": "ArrowLeft"
    }
  ],
  "app:go-forward": [
    {
      "modifiers": [
        "Alt"
      ],
      "key": "ArrowRight"
    }
  ],
  "daily-notes": [
    {
      "modifiers": [
        "Mod"
      ],
      "key": "T"
    }
  ],
  "editor:cycle-list-checklist": [
    {
      "modifiers": [
        "Mod"
      ],
      "key": "Enter"
    }
  ],
  "editor:open-link-in-new-leaf": []
}